errors/__init__.py
errors/errors.py
membind/__init__.py
membind/memory.py
memquery/__init__.py
memquery/__version__.py
memquery/memquery.py
memquery-0.1.1.dist-info/METADATA
memquery-0.1.1.dist-info/WHEEL
memquery-0.1.1.dist-info/top_level.txt
memquery-0.1.1.dist-info/RECORD
